{
  "plans": [
    {
      "id": "StrongLifts 5x5",
      "days": [
        {
          "id": "A",
          "exercises": [
            {
              "id": "Squat",
              "sets": [
                { "id": "set_01", "weight": 50, "reps": 5 },
                { "id": "set_02", "weight": 50, "reps": 5 },
                { "id": "set_03", "weight": 50, "reps": 5 },
                { "id": "set_04", "weight": 50, "reps": 5 },
                { "id": "set_05", "weight": 50, "reps": 5 }
              ]
            },
            {
              "id": "Bench Press",
              "sets": [
                { "id": "set_01", "weight": 50, "reps": 5 },
                { "id": "set_02", "weight": 50, "reps": 5 },
                { "id": "set_03", "weight": 50, "reps": 5 },
                { "id": "set_04", "weight": 50, "reps": 5 },
                { "id": "set_05", "weight": 50, "reps": 5 }
              ]
            },
            {
              "id": "Barbell Row",
              "sets": [
                { "id": "set_01", "weight": 50, "reps": 5 },
                { "id": "set_02", "weight": 50, "reps": 5 },
                { "id": "set_03", "weight": 50, "reps": 5 },
                { "id": "set_04", "weight": 50, "reps": 5 },
                { "id": "set_05", "weight": 50, "reps": 5 }
              ]
            }
          ]
        },
        {
          "id": "B",
          "exercises": [
            {
              "id": "Squat",
              "sets": [
                { "id": "set_01", "weight": 50, "reps": 5 },
                { "id": "set_02", "weight": 50, "reps": 5 },
                { "id": "set_03", "weight": 50, "reps": 5 },
                { "id": "set_04", "weight": 50, "reps": 5 },
                { "id": "set_05", "weight": 50, "reps": 5 }
              ]
            },
            {
              "id": "Overhead Press",
              "sets": [
                { "id": "set_01", "weight": 50, "reps": 5 },
                { "id": "set_02", "weight": 50, "reps": 5 },
                { "id": "set_03", "weight": 50, "reps": 5 },
                { "id": "set_04", "weight": 50, "reps": 5 },
                { "id": "set_05", "weight": 50, "reps": 5 }
              ]
            },
            {
              "id": "Deadlift",
              "sets": [
                { "id": "set_01", "weight": 50, "reps": 5 }
              ]
            }
          ]
        }
      ]
    }
  ]
}
